nested_data_helper/__init__.py
nested_data_helper/navigation.py
nested_data_helper/pathfinder.py
nested_data_helper-1.0.2.dist-info/LICENSE
nested_data_helper-1.0.2.dist-info/METADATA
nested_data_helper-1.0.2.dist-info/WHEEL
nested_data_helper-1.0.2.dist-info/top_level.txt
nested_data_helper-1.0.2.dist-info/RECORD
