Metadata-Version: 2.1
Name: nested-data-helper
Version: 1.0.2
Summary: Help you find the data nested deep in your data
Author-email: Roman Ma <romanma0508@gmail.com>
License: GNU GENERAL PUBLIC LICENSE
Project-URL: Homepage, https://github.com/malokroman/nested-data-helper
Keywords: nested-data,nosql,data-engineering
Classifier: Programming Language :: Python
Classifier: Programming Language :: Python :: 3
Requires-Python: >=3.6
License-File: LICENSE
Provides-Extra: dev
Requires-Dist: ruff; extra == "dev"
Requires-Dist: bumpver; extra == "dev"
Requires-Dist: isort; extra == "dev"
Requires-Dist: pip-tools; extra == "dev"
